fastapi_safeguard.py
fastapi_safeguard-0.1.0.dist-info/licenses/LICENSE
fastapi_safeguard-0.1.0.dist-info/METADATA
fastapi_safeguard-0.1.0.dist-info/WHEEL
fastapi_safeguard-0.1.0.dist-info/top_level.txt
fastapi_safeguard-0.1.0.dist-info/RECORD
