Metadata-Version: 2.4
Name: fastapi-safeguard
Version: 0.1.0
Summary: Startup-time security posture and baseline management plugin for FastAPI applications.
Author-email: Mateusz Wagner <mateuszwag@gmail.com>
License: MIT License
Project-URL: Homepage, https://github.com/mateush/fastapi-safeguard
Project-URL: Repository, https://github.com/mateush/fastapi-safeguard
Project-URL: Issues, https://github.com/mateush/fastapi-safeguard/issues
Project-URL: Changelog, https://github.com/mateush/fastapi-safeguard/releases
Keywords: fastapi,security,owasp,baseline,lint,api,hardening
Classifier: Development Status :: 3 - Alpha
Classifier: Intended Audience :: Developers
Classifier: License :: OSI Approved :: MIT License
Classifier: Programming Language :: Python :: 3
Classifier: Programming Language :: Python :: 3.9
Classifier: Programming Language :: Python :: 3.10
Classifier: Programming Language :: Python :: 3.11
Classifier: Programming Language :: Python :: 3.12
Classifier: Programming Language :: Python :: 3.13
Classifier: Framework :: FastAPI
Classifier: Topic :: Security
Classifier: Topic :: Software Development :: Quality Assurance
Classifier: Topic :: Internet :: WWW/HTTP
Requires-Python: >=3.9
License-File: LICENSE
Requires-Dist: fastapi<1.0.0,>=0.110.0
Provides-Extra: dev
Requires-Dist: pytest>=8.0.0; extra == "dev"
Requires-Dist: pytest-cov>=5.0.0; extra == "dev"
Requires-Dist: pytest-asyncio>=0.23.0; extra == "dev"
Requires-Dist: httpx>=0.27.0; extra == "dev"
Dynamic: license-file
